csv_to_ascii_table/__init__.py
csv_to_ascii_table/csv2table.py
csv_to_ascii_table-0.5.1.dist-info/LICENSE
csv_to_ascii_table-0.5.1.dist-info/METADATA
csv_to_ascii_table-0.5.1.dist-info/WHEEL
csv_to_ascii_table-0.5.1.dist-info/entry_points.txt
csv_to_ascii_table-0.5.1.dist-info/top_level.txt
csv_to_ascii_table-0.5.1.dist-info/RECORD
