Metadata-Version: 2.1
Name: csv-to-ascii-table
Version: 0.5.1
Summary: An asynchronous CSV to ASCII table converter
Home-page: https://github.com/rowingdude/ascii_table_generator
Author: Benjamin Cance
Author-email: canceb@gmail.com
Classifier: Development Status :: 3 - Alpha
Classifier: Intended Audience :: Developers
Classifier: License :: OSI Approved :: MIT License
Classifier: Operating System :: OS Independent
Classifier: Programming Language :: Python :: 3
Classifier: Programming Language :: Python :: 3.7
Classifier: Programming Language :: Python :: 3.8
Classifier: Programming Language :: Python :: 3.9
Requires-Python: >=3.7
License-File: LICENSE
Requires-Dist: asyncio
